riv_hex_table/__init__.py
riv_hex_table/hex_card.py
riv_hex_table/hex_subheader.py
riv_hex_table/hex_table.py
riv_hex_table-0.2.2.dist-info/LICENSE
riv_hex_table-0.2.2.dist-info/METADATA
riv_hex_table-0.2.2.dist-info/WHEEL
riv_hex_table-0.2.2.dist-info/top_level.txt
riv_hex_table-0.2.2.dist-info/RECORD
